titanarchive/__init__.py
titanarchive/titanarchive.py
titanarchive-2.1.data/data/DLLs/TitanArchive64-7z.dll
titanarchive-2.1.data/data/DLLs/TitanArchive64.dll
titanarchive-2.1.dist-info/LICENSE
titanarchive-2.1.dist-info/METADATA
titanarchive-2.1.dist-info/WHEEL
titanarchive-2.1.dist-info/top_level.txt
titanarchive-2.1.dist-info/RECORD
