Metadata-Version: 2.1
Name: titanarchive
Version: 2.1
Summary: An easy to use multiplatform archive extraction wrapper library for 7-Zip
Home-page: https://github.com/4d61726b/TitanArchive
License: LGPL-2.1
Requires-Python: >=3
License-File: LICENSE
